renumics/spotlight/__init__.py
renumics/spotlight/__version__.py
renumics/spotlight/analysis/__init__.py
renumics/spotlight/analysis/analyzers/__init__.py
renumics/spotlight/analysis/analyzers/cleanlab.py
renumics/spotlight/analysis/analyzers/cleanvision.py
renumics/spotlight/analysis/decorator.py
renumics/spotlight/analysis/registry.py
renumics/spotlight/analysis/typing.py
renumics/spotlight/app.py
renumics/spotlight/app_config.py
renumics/spotlight/appdirs.py
renumics/spotlight/backend/__init__.py
renumics/spotlight/backend/apis/__init__.py
renumics/spotlight/backend/apis/plugins.py
renumics/spotlight/backend/apis/websocket.py
renumics/spotlight/backend/config.py
renumics/spotlight/backend/exceptions.py
renumics/spotlight/backend/middlewares/__init__.py
renumics/spotlight/backend/middlewares/timing.py
renumics/spotlight/backend/statics/.vite/manifest.json
renumics/spotlight/backend/statics/App.d.ts
renumics/spotlight/backend/statics/api/config.d.ts
renumics/spotlight/backend/statics/api/errors.d.ts
renumics/spotlight/backend/statics/api/index.d.ts
renumics/spotlight/backend/statics/application.d.ts
renumics/spotlight/backend/statics/assets/SpectrogramWorker-BlZvv9d2.js
renumics/spotlight/backend/statics/assets/relevanceWorker-CDfSO-Dl.js
renumics/spotlight/backend/statics/browser.d.ts
renumics/spotlight/backend/statics/client/apis/ConfigApi.d.ts
renumics/spotlight/backend/statics/client/apis/DefaultApi.d.ts
renumics/spotlight/backend/statics/client/apis/FilebrowserApi.d.ts
renumics/spotlight/backend/statics/client/apis/IssuesApi.d.ts
renumics/spotlight/backend/statics/client/apis/LayoutApi.d.ts
renumics/spotlight/backend/statics/client/apis/PluginsApi.d.ts
renumics/spotlight/backend/statics/client/apis/TableApi.d.ts
renumics/spotlight/backend/statics/client/apis/index.d.ts
renumics/spotlight/backend/statics/client/index.d.ts
renumics/spotlight/backend/statics/client/models/AnalysisInfo.d.ts
renumics/spotlight/backend/statics/client/models/Column.d.ts
renumics_spotlight-1.7.1.dist-info/METADATA
renumics_spotlight-1.7.1.dist-info/WHEEL
renumics_spotlight-1.7.1.dist-info/entry_points.txt
renumics_spotlight-1.7.1.dist-info/licenses/LICENSE
renumics_spotlight-1.7.1.dist-info/RECORD
