Metadata-Version: 2.4
Name: renumics-spotlight
Version: 1.7.1
Summary: Visualize and maintain datasets to develop and understand data-driven algorithms.
License-Expression: MIT
License-File: LICENSE
Keywords: data curation,machine learning,data science,visualization,pandas,ai
Author: Renumics GmbH
Author-email: info@renumics.com
Requires-Python: >=3.9, <4.0
Classifier: Development Status :: 5 - Production/Stable
Classifier: Framework :: FastAPI
Classifier: Intended Audience :: Developers
Classifier: Intended Audience :: Science/Research
Classifier: Intended Audience :: Manufacturing
Classifier: Intended Audience :: Information Technology
Classifier: Natural Language :: English
Classifier: Operating System :: POSIX :: Linux
Classifier: Operating System :: Microsoft :: Windows
Classifier: Operating System :: MacOS
Classifier: Programming Language :: JavaScript
Classifier: Topic :: Scientific/Engineering
Classifier: Topic :: Scientific/Engineering :: Artificial Intelligence
Classifier: Topic :: Scientific/Engineering :: Visualization
Classifier: Topic :: Scientific/Engineering :: Information Analysis
Classifier: Typing :: Typed
Provides-Extra: all
Provides-Extra: analyzers
Requires-Dist: aiofiles
Requires-Dist: appdirs
Requires-Dist: av
Requires-Dist: cleanlab ; extra == "all"
Requires-Dist: cleanlab ; extra == "analyzers"
Requires-Dist: cleanvision ; extra == "all"
Requires-Dist: cleanvision ; extra == "analyzers"
Requires-Dist: click
Requires-Dist: databases[sqlite] (>=0.1.3)
Requires-Dist: datasets[audio] (>=2.12.0)
Requires-Dist: diskcache
Requires-Dist: fastapi (>=0.65.2)
Requires-Dist: filetype
Requires-Dist: h5py (>3.0)
Requires-Dist: httptools
Requires-Dist: httpx (>=0.23.0)
Requires-Dist: imagecodecs ; platform_machine != "arm64"
Requires-Dist: imageio (>=2.18.0)
Requires-Dist: importlib_resources (<5.8.0)
Requires-Dist: ipywidgets
Requires-Dist: jinja2
Requires-Dist: loguru
Requires-Dist: networkx
Requires-Dist: numba
Requires-Dist: numpy
Requires-Dist: orjson
Requires-Dist: packaging
Requires-Dist: pandas
Requires-Dist: pillow (>=10.0.0)
Requires-Dist: prettytable
Requires-Dist: py-machineid
Requires-Dist: pyarrow
Requires-Dist: pydantic (>=2.0.0,<3.0.0)
Requires-Dist: pydantic-settings (>=2.0.0,<3.0.0)
Requires-Dist: pygltflib (>=1.15.1)
Requires-Dist: requests (>=2.31)
Requires-Dist: rsa
Requires-Dist: scikit-image
Requires-Dist: scikit-learn
Requires-Dist: setuptools
Requires-Dist: toml
Requires-Dist: tqdm
Requires-Dist: transformers
Requires-Dist: trimesh
Requires-Dist: typing-extensions
Requires-Dist: umap-learn
Requires-Dist: uvicorn (>=0.22)
Requires-Dist: uvloop (>=0.17.0) ; sys_platform == "Linux" or sys_platform == "Darwin"
Requires-Dist: validators
Requires-Dist: websockets
